[
  {
    "sigla": "3R-1",
    "nome": "PLATAFORMA 3R-1",
    "campos": "PEROÁ",
    "bacia": "ESPÍRITO SANTO",
    "operador": "3R PETROLEUM OFFSHORE S.A.",
    "classificacao": "Plataforma Fixa - Jaqueta",
    "lamina_agua_m": 67,
    "sistema_escoamento": "Duto",
    "ano_inicio_operacao": 2006,
    "latitude": -19.56278333,
    "longitude": -39.25528333,
    "capacidade_petroleo_bbl_d": null,
    "capacidade_gas_mil_m3_d": null,
    "data_inicio_producao": "22/02/2006",
    "fonte": "https://www.gov.br/cgu/pt-br/assuntos/auditoria-e-fiscalizacao/avaliacao-da-gestao-dos-administradores/prestacao-de-contas-do-presidente-da-republica/arquivos/2006/volume-iv/comentset.pdf",
    "pais": "Brasil",
    "status": "operando"
  },
  {
    "sigla": "3R-2",
    "nome": "PLATAFORMA 3R-2",
    "campos": "PAPA-TERRA",
    "bacia": "CAMPOS",
    "operador": "3R PETROLEUM OFFSHORE S.A.",
    "classificacao": "Tension Leg Platform - TLP",
    "lamina_agua_m": 1185,
    "sistema_escoamento": "Duto",
    "ano_inicio_operacao": 2014,
    "latitude": -23.51603889,
    "longitude": -41.0612925,
    "capacidade_petroleo_bbl_d": null,
    "capacidade_gas_mil_m3_d": null,
    "data_inicio_producao": "11/11/2013",
    "fonte": "https://mz-filemanager.s3.amazonaws.com/25fdf098-34f5-4608-b7fa-17d60b2de47d/comunicados-ao-mercadocentral-de-downloads/71e1cc49b3bc713ebecefa0e2c3018745960143ce6150ffc2b90a4dd2f22aee6/startup_of_platform_p61_in_papa_terra_field.pdf",
    "pais": "Brasil",
    "status": "operando"
  },
  {
    "sigla": "3R-3",
    "nome": "PLATAFORMA 3R-3",
    "campos": "PAPA-TERRA",
    "bacia": "CAMPOS",
    "operador": "3R PETROLEUM OFFSHORE S.A.",
    "classificacao": "Floating Production Storage Offloading - FPSO",
    "lamina_agua_m": 1165,
    "sistema_escoamento": "Navio Aliviador",
    "ano_inicio_operacao": 2013,
    "latitude": -23.51396333,
    "longitude": -41.06461833,
    "capacidade_petroleo_bbl_d": 140000,
    "capacidade_gas_mil_m3_d": 1000,
    "data_inicio_producao": "11/11/2013",
    "fonte": "https://economia.uol.com.br/noticias/reuters/2013/11/12/petrobras-inicia-producao-no-campo-de-papa-terra.htm",
    "pais": "Brasil",
    "status": "operando"
  },
  {
    "sigla": "FPSOATLANTA",
    "nome": "FPSO ATLANTA",
    "campos": "ATLANTA",
    "bacia": "SANTOS",
    "operador": "BRAVA ENERGIA S.A.",
    "classificacao": "Floating Production Storage Offloading - FPSO",
    "lamina_agua_m": 1550,
    "sistema_escoamento": "Navio Aliviador",
    "ano_inicio_operacao": 2024,
    "latitude": -24.09909722,
    "longitude": -41.88699167,
    "capacidade_petroleo_bbl_d": 50000,
    "capacidade_gas_mil_m3_d": 350,
    "data_inicio_producao": "31/12/2024",
    "fonte": "https://bravaenergia.com/en/noticias/brava-energia-announces-the-first-oil-from-the-atlanta-field-definitive-system/",
    "pais": "Brasil",
    "status": "operando"
  },
  {
    "sigla": "CVIX",
    "nome": "FPSO CIDADE DE VITÓRIA",
    "campos": "GOLFINHO",
    "bacia": "ESPÍRITO SANTO",
    "operador": "BW ENERGY MAROMBA DO BRASIL LTDA",
    "classificacao": "Floating Production Storage Offloading - FPSO",
    "lamina_agua_m": 1386,
    "sistema_escoamento": "Navio Aliviador",
    "ano_inicio_operacao": 2007,
    "latitude": -20.04277778,
    "longitude": -39.52555556,
    "capacidade_petroleo_bbl_d": 100637,
    "capacidade_gas_mil_m3_d": 3500,
    "data_inicio_producao": "20/11/2007",
    "fonte": "https://www.offshore-mag.com/articles/2007/11/golfinho-fpso-goes-online.html",
    "pais": "Brasil",
    "status": "operando"
  },
  {
    "sigla": "FPSO BACALHAU",
    "nome": "FPSO BACALHAU",
    "campos": "BACALHAU / BACALHAU NORTE",
    "bacia": "SANTOS",
    "operador": "EQUINOR BRASIL ENERGIA LTDA.",
    "classificacao": "Floating Production Storage Offloading - FPSO",
    "lamina_agua_m": 2100,
    "sistema_escoamento": "Navio Aliviador",
    "ano_inicio_operacao": 2025,
    "latitude": -25.47606333,
    "longitude": -43.93906806,
    "capacidade_petroleo_bbl_d": 220000,
    "capacidade_gas_mil_m3_d": 15000,
    "data_inicio_producao": "15/10/2025",
    "fonte": "https://www.equinor.com/news/20251016-bacalhau-production-started",
    "pais": "Brasil",
    "status": "operando"
  },
  {
    "sigla": "FPCI",
    "nome": "FPSO CIDADE DE ITAJAÍ",
    "campos": "BAÚNA",
    "bacia": "SANTOS",
    "operador": "KAROON PETRÓLEO E GÁS LTDA.",
    "classificacao": "Floating Production Storage Offloading - FPSO",
    "lamina_agua_m": 275,
    "sistema_escoamento": "Navio Aliviador",
    "ano_inicio_operacao": 2013,
    "latitude": -26.46462444,
    "longitude": -46.53012444,
    "capacidade_petroleo_bbl_d": 80000,
    "capacidade_gas_mil_m3_d": 2000,
    "data_inicio_producao": "16/02/2013",
    "fonte": "https://financialreports.eu/filings/petrobras-petroleo-brasileiro-sa/foreign-filer-report/2013/27953076/",
    "pais": "Brasil",
    "status": "operando"
  },
  {
    "sigla": "PCP-I",
    "nome": "PLATAFORMA DE CARAPEBA 1",
    "campos": "CARAPEBA",
    "bacia": "CAMPOS",
    "operador": "PERENCO PETRÓLEO E GÁS DO BRASIL LTDA.",
    "classificacao": "Plataforma Fixa - Jaqueta",
    "lamina_agua_m": 86,
    "sistema_escoamento": "Duto",
    "ano_inicio_operacao": 1988,
    "latitude": -22.24508639,
    "longitude": -40.44303222,
    "capacidade_petroleo_bbl_d": null,
    "capacidade_gas_mil_m3_d": null,
    "data_inicio_producao": "31/12/1988",
    "fonte": "https://www.gov.br/anp/pt-br/assuntos/exploracao-e-producao-de-oleo-e-gas/desenvolvimento-e-producao/pd/carapeba.pdf/@@download/file",
    "pais": "Brasil",
    "status": "operando"
  },
  {
    "sigla": "PCP-II",
    "nome": "PLATAFORMA DE CARAPEBA 2",
    "campos": "CARAPEBA",
    "bacia": "CAMPOS",
    "operador": "PERENCO PETRÓLEO E GÁS DO BRASIL LTDA.",
    "classificacao": "Plataforma Fixa - Jaqueta",
    "lamina_agua_m": 87,
    "sistema_escoamento": "Duto",
    "ano_inicio_operacao": 1988,
    "latitude": -22.23357944,
    "longitude": -40.415245,
    "capacidade_petroleo_bbl_d": null,
    "capacidade_gas_mil_m3_d": null,
    "data_inicio_producao": "31/12/1988",
    "fonte": "https://www.gov.br/anp/pt-br/assuntos/exploracao-e-producao-de-oleo-e-gas/desenvolvimento-e-producao/pd/carapeba.pdf/@@download/file",
    "pais": "Brasil",
    "status": "operando"
  },
  {
    "sigla": "PCP-III",
    "nome": "PLATAFORMA DE CARAPEBA 3",
    "campos": "CARAPEBA",
    "bacia": "CAMPOS",
    "operador": "PERENCO PETRÓLEO E GÁS DO BRASIL LTDA.",
    "classificacao": "Plataforma Fixa - Jaqueta",
    "lamina_agua_m": 86,
    "sistema_escoamento": "Duto",
    "ano_inicio_operacao": 1994,
    "latitude": -22.24496611,
    "longitude": -40.44234222,
    "capacidade_petroleo_bbl_d": null,
    "capacidade_gas_mil_m3_d": null,
    "data_inicio_producao": "31/12/1988",
    "fonte": "https://www.gov.br/anp/pt-br/assuntos/exploracao-e-producao-de-oleo-e-gas/desenvolvimento-e-producao/pd/carapeba.pdf/@@download/file",
    "pais": "Brasil",
    "status": "operando"
  },
  {
    "sigla": "PPG-1A",
    "nome": "PLATAFORMA DE PARGO 1A",
    "campos": "PARGO",
    "bacia": "CAMPOS",
    "operador": "PERENCO PETRÓLEO E GÁS DO BRASIL LTDA.",
    "classificacao": "Plataforma Fixa - Jaqueta",
    "lamina_agua_m": 101,
    "sistema_escoamento": "Duto",
    "ano_inicio_operacao": 1988,
    "latitude": -22.25555306,
    "longitude": -40.32994917,
    "capacidade_petroleo_bbl_d": 30000,
    "capacidade_gas_mil_m3_d": 170,
    "data_inicio_producao": "31/12/1988",
    "fonte": "https://repositorio.ufpb.br/jspui/bitstream/123456789/12184/1/Arquivototal.pdf",
    "pais": "Brasil",
    "status": "operando"
  },
  {
    "sigla": "PVM-1",
    "nome": "PLATAFORMA DE VERMELHO 1",
    "campos": "VERMELHO",
    "bacia": "CAMPOS",
    "operador": "PERENCO PETRÓLEO E GÁS DO BRASIL LTDA.",
    "classificacao": "Plataforma Fixa - Jaqueta",
    "lamina_agua_m": 80,
    "sistema_escoamento": "Duto",
    "ano_inicio_operacao": 1989,
    "latitude": -22.16066028,
    "longitude": -40.2787175,
    "capacidade_petroleo_bbl_d": null,
    "capacidade_gas_mil_m3_d": null,
    "data_inicio_producao": "31/01/1989",
    "fonte": "https://www.gov.br/anp/pt-br/assuntos/exploracao-e-producao-de-oleo-e-gas/desenvolvimento-e-producao/pd/vermelho.pdf/@@download/file",
    "pais": "Brasil",
    "status": "operando"
  },
  {
    "sigla": "PVM-3",
    "nome": "PLATAFORMA DE VERMELHO 3",
    "campos": "VERMELHO",
    "bacia": "CAMPOS",
    "operador": "PERENCO PETRÓLEO E GÁS DO BRASIL LTDA.",
    "classificacao": "Plataforma Fixa - Jaqueta",
    "lamina_agua_m": 82,
    "sistema_escoamento": "Duto",
    "ano_inicio_operacao": 1989,
    "latitude": -22.189705,
    "longitude": -40.30321833,
    "capacidade_petroleo_bbl_d": null,
    "capacidade_gas_mil_m3_d": null,
    "data_inicio_producao": "31/01/1989",
    "fonte": "https://www.gov.br/anp/pt-br/assuntos/exploracao-e-producao-de-oleo-e-gas/desenvolvimento-e-producao/pd/vermelho.pdf/@@download/file",
    "pais": "Brasil",
    "status": "operando"
  },
  {
    "sigla": "FCDA",
    "nome": "FPSO CIDADE DE ANCHIETA",
    "campos": "AnC_Jubarte_Nordeste / AnC_Jubarte_Sudoeste / ARGONAUTA / JUBARTE",
    "bacia": "CAMPOS",
    "operador": "PETRÓLEO BRASILEIRO S.A. - PETROBRAS",
    "classificacao": "Floating Production Storage Offloading - FPSO",
    "lamina_agua_m": 1221,
    "sistema_escoamento": "Navio Aliviador",
    "ano_inicio_operacao": 2012,
    "latitude": -21.33756667,
    "longitude": -40.05720278,
    "capacidade_petroleo_bbl_d": 100000,
    "capacidade_gas_mil_m3_d": 3500,
    "data_inicio_producao": "10/09/2012",
    "fonte": "https://www.sbmoffshore.com/wp-content/uploads/2024/03/pr-2012-09-17-on-hire-fpso-cdde-anchieta2.pdf",
    "pais": "Brasil",
    "status": "operando"
  },
  {
    "sigla": "FPADG",
    "nome": "FPSO ALEXANDRE DE GUSMÃO",
    "campos": "AnC_MERO / MERO",
    "bacia": "SANTOS",
    "operador": "PETRÓLEO BRASILEIRO S.A. - PETROBRAS",
    "classificacao": "Floating Production Storage Offloading - FPSO",
    "lamina_agua_m": 1890,
    "sistema_escoamento": "Navio Aliviador",
    "ano_inicio_operacao": 2025,
    "latitude": -24.55964917,
    "longitude": -42.18826083,
    "capacidade_petroleo_bbl_d": 180000,
    "capacidade_gas_mil_m3_d": 12000,
    "data_inicio_producao": "24/05/2025",
    "fonte": "https://agencia.petrobras.com.br/pt/w/fpso-alexandre-de-gusmao-inicia-operacao-no-campo-de-mero-na-bacia-de-santos",
    "pais": "Brasil",
    "status": "operando"
  },
  {
    "sigla": "FPAGA",
    "nome": "FPSO ANITA GARIBALDI",
    "campos": "ESPADIM / MARLIM / MARLIM SUL / VOADOR",
    "bacia": "CAMPOS",
    "operador": "PETRÓLEO BRASILEIRO S.A. - PETROBRAS",
    "classificacao": "Floating Production Storage Offloading - FPSO",
    "lamina_agua_m": 670,
    "sistema_escoamento": "Navio Aliviador e Duto",
    "ano_inicio_operacao": 2023,
    "latitude": -22.39583639,
    "longitude": -40.10831417,
    "capacidade_petroleo_bbl_d": 80000,
    "capacidade_gas_mil_m3_d": 6622,
    "data_inicio_producao": "16/08/2023",
    "fonte": "https://agencia.petrobras.com.br/en/w/negocio/plataforma-anita-garibaldi-entra-em-producao-na-bacia-de-campos",
    "pais": "Brasil",
    "status": "operando"
  },
  {
    "sigla": "FPANE",
    "nome": "FPSO ANNA NERY",
    "campos": "MARLIM / MARLIM SUL",
    "bacia": "CAMPOS",
    "operador": "PETRÓLEO BRASILEIRO S.A. - PETROBRAS",
    "classificacao": "Floating Production Storage Offloading - FPSO",
    "lamina_agua_m": 927,
    "sistema_escoamento": "Navio Aliviador e Duto",
    "ano_inicio_operacao": 2023,
    "latitude": -22.46391639,
    "longitude": -40.05731667,
    "capacidade_petroleo_bbl_d": 70000,
    "capacidade_gas_mil_m3_d": 3792,
    "data_inicio_producao": "07/05/2023",
    "fonte": "https://transparencia.petrobras.com.br/documents/1357439/1361156/Relatorio%2Bde%2BGestao%2B-%2BPetrobras%2B-%2B2022.pdf",
    "pais": "Brasil",
    "status": "operando"
  },
  {
    "sigla": "FPBAR",
    "nome": "FPSO ALMIRANTE BARROSO",
    "campos": "BÚZIOS / BÚZIOS_ECO / TAMBUATÁ",
    "bacia": "SANTOS",
    "operador": "PETRÓLEO BRASILEIRO S.A. - PETROBRAS",
    "classificacao": "Floating Production Storage Offloading - FPSO",
    "lamina_agua_m": 1900,
    "sistema_escoamento": "Navio Aliviador",
    "ano_inicio_operacao": 2023,
    "latitude": -24.5925325,
    "longitude": -42.56725167,
    "capacidade_petroleo_bbl_d": 173640,
    "capacidade_gas_mil_m3_d": 6291,
    "data_inicio_producao": "31/05/2023",
    "fonte": "https://agencia.petrobras.com.br/w/negocio/fpso-almirante-barroso-comeca-a-produzir-no-campo-de-buzios",
    "pais": "Brasil",
    "status": "operando"
  },
  {
    "sigla": "FPCAR",
    "nome": "FPSO CIDADE DE ANGRA DOS REIS",
    "campos": "AnC_TUPI / SUL DE TUPI / TUPI",
    "bacia": "SANTOS",
    "operador": "PETRÓLEO BRASILEIRO S.A. - PETROBRAS",
    "classificacao": "Floating Production Storage Offloading - FPSO",
    "lamina_agua_m": 2140,
    "sistema_escoamento": "Navio Aliviador",
    "ano_inicio_operacao": 2010,
    "latitude": -25.54481667,
    "longitude": -42.84021389,
    "capacidade_petroleo_bbl_d": 100637,
    "capacidade_gas_mil_m3_d": 5000,
    "data_inicio_producao": "28/10/2010",
    "fonte": "https://www.perfilnews.com.br/2010/12/09/producao-de-gas-da-petrobras-aumenta-7-8-por-cento/",
    "pais": "Brasil",
    "status": "operando"
  },
  {
    "sigla": "FPCGZ",
    "nome": "FPSO CIDADE DE CAMPOS DOS GOYTACAZES",
    "campos": "ESPADARTE / TARTARUGA VERDE / TARTARUGA VERDE SUDOESTE",
    "bacia": "CAMPOS",
    "operador": "PETRÓLEO BRASILEIRO S.A. - PETROBRAS",
    "classificacao": "Floating Production Storage Offloading - FPSO",
    "lamina_agua_m": 765,
    "sistema_escoamento": "Navio Aliviador",
    "ano_inicio_operacao": 2018,
    "latitude": -22.95337917,
    "longitude": -40.72554611,
    "capacidade_petroleo_bbl_d": 150000,
    "capacidade_gas_mil_m3_d": 3300,
    "data_inicio_producao": "22/06/2018",
    "fonte": "https://www.modec.com/news/2018/20180626.html",
    "pais": "Brasil",
    "status": "operando"
  },
  {
    "sigla": "FPCIB",
    "nome": "FPSO CIDADE DE ILHABELA",
    "campos": "NORDESTE DE SAPINHOÁ / NOROESTE DE SAPINHOÁ / SAPINHOÁ / SUDOESTE DE SAPINHOÁ",
    "bacia": "SANTOS",
    "operador": "PETRÓLEO BRASILEIRO S.A. - PETROBRAS",
    "classificacao": "Floating Production Storage Offloading - FPSO",
    "lamina_agua_m": 2140,
    "sistema_escoamento": "Navio Aliviador",
    "ano_inicio_operacao": 2014,
    "latitude": -25.67280556,
    "longitude": -43.20619167,
    "capacidade_petroleo_bbl_d": 150000,
    "capacidade_gas_mil_m3_d": 6000,
    "data_inicio_producao": "24/11/2014",
    "fonte": "https://www.sbmoffshore.com/newsroom/fpso-cidade-de-ilhabela-producing-and-hire/",
    "pais": "Brasil",
    "status": "operando"
  },
  {
    "sigla": "FPCIG",
    "nome": "FPSO CIDADE DE ITAGUAÍ",
    "campos": "TUPI",
    "bacia": "SANTOS",
    "operador": "PETRÓLEO BRASILEIRO S.A. - PETROBRAS",
    "classificacao": "Floating Production Storage Offloading - FPSO",
    "lamina_agua_m": 2240,
    "sistema_escoamento": "Navio Aliviador",
    "ano_inicio_operacao": 2015,
    "latitude": -25.14156917,
    "longitude": -42.94469694,
    "capacidade_petroleo_bbl_d": 150955,
    "capacidade_gas_mil_m3_d": 8000,
    "data_inicio_producao": "31/07/2015",
    "fonte": "https://www.galp.com/corp/en/investors/publications-and-announcements/investor-announcements/investor-announcement/id/601/start-of-production-of-fpso-cidade-de-itaguai-4-in-lulairacema-field",
    "pais": "Brasil",
    "status": "operando"
  },
  {
    "sigla": "FPCMB",
    "nome": "FPSO CIDADE DE MANGARATIBA",
    "campos": "TUPI",
    "bacia": "SANTOS",
    "operador": "PETRÓLEO BRASILEIRO S.A. - PETROBRAS",
    "classificacao": "Floating Production Storage Offloading - FPSO",
    "lamina_agua_m": 2200,
    "sistema_escoamento": "Navio Aliviador",
    "ano_inicio_operacao": 2014,
    "latitude": -25.20407778,
    "longitude": -42.87856389,
    "capacidade_petroleo_bbl_d": 150955,
    "capacidade_gas_mil_m3_d": 8000,
    "data_inicio_producao": "14/10/2014",
    "fonte": "https://news.cision.com/pt/galp-energia/r/fpso-cidade-de-mangaratiba-entra-em-operacao-e-da-inicio-a-producao-comercial-na-area-de-iracema-sul%2Cc635489639400000000",
    "pais": "Brasil",
    "status": "operando"
  },
  {
    "sigla": "FPCMC",
    "nome": "FPSO CIDADE DE MARICÁ",
    "campos": "AnC_TUPI / SUL DE TUPI / TUPI",
    "bacia": "SANTOS",
    "operador": "PETRÓLEO BRASILEIRO S.A. - PETROBRAS",
    "classificacao": "Floating Production Storage Offloading - FPSO",
    "lamina_agua_m": 2120,
    "sistema_escoamento": "Navio Aliviador",
    "ano_inicio_operacao": 2016,
    "latitude": -25.44884861,
    "longitude": -42.75307194,
    "capacidade_petroleo_bbl_d": 150000,
    "capacidade_gas_mil_m3_d": 6000,
    "data_inicio_producao": "07/02/2016",
    "fonte": "https://www.sbmoffshore.com/newsroom/fpso-cidade-de-marica-producing-and-hire/",
    "pais": "Brasil",
    "status": "operando"
  },
  {
    "sigla": "FPCP",
    "nome": "FPSO CIDADE DE PARATY",
    "campos": "AnC_TUPI / SUL DE TUPI / TUPI",
    "bacia": "SANTOS",
    "operador": "PETRÓLEO BRASILEIRO S.A. - PETROBRAS",
    "classificacao": "Floating Production Storage Offloading - FPSO",
    "lamina_agua_m": 2120,
    "sistema_escoamento": "Navio Aliviador",
    "ano_inicio_operacao": 2012,
    "latitude": -25.39437222,
    "longitude": -42.76180278,
    "capacidade_petroleo_bbl_d": 120139,
    "capacidade_gas_mil_m3_d": 5000,
    "data_inicio_producao": "06/06/2013",
    "fonte": "https://www.galp.com/corp/Portals/0/Recursos/Investidores/SharedResources/Resultados/PT/2014-2T-RT/ACF/2Q14RESULTS.pdf",
    "pais": "Brasil",
    "status": "operando"
  },
  {
    "sigla": "FPCSP",
    "nome": "FPSO CIDADE DE SÃO PAULO",
    "campos": "NORDESTE DE SAPINHOÁ / NOROESTE DE SAPINHOÁ / SAPINHOÁ / SUDOESTE DE SAPINHOÁ",
    "bacia": "SANTOS",
    "operador": "PETRÓLEO BRASILEIRO S.A. - PETROBRAS",
    "classificacao": "Floating Production Storage Offloading - FPSO",
    "lamina_agua_m": 2140,
    "sistema_escoamento": "Navio Aliviador",
    "ano_inicio_operacao": 2013,
    "latitude": -25.79933417,
    "longitude": -43.26283917,
    "capacidade_petroleo_bbl_d": 120000,
    "capacidade_gas_mil_m3_d": 5000,
    "data_inicio_producao": "05/01/2013",
    "fonte": "https://exame.com/negocios/petrobras-inicia-producao-comercial-em-campo-gigante-2",
    "pais": "Brasil",
    "status": "operando"
  },
  {
    "sigla": "FPCSQ",
    "nome": "FPSO CIDADE DE SAQUAREMA",
    "campos": "AnC_TUPI / SUL DE TUPI / TUPI",
    "bacia": "SANTOS",
    "operador": "PETRÓLEO BRASILEIRO S.A. - PETROBRAS",
    "classificacao": "Floating Production Storage Offloading - FPSO",
    "lamina_agua_m": 2120,
    "sistema_escoamento": "Navio Aliviador",
    "ano_inicio_operacao": 2016,
    "latitude": -25.4912675,
    "longitude": -42.78126306,
    "capacidade_petroleo_bbl_d": 150000,
    "capacidade_gas_mil_m3_d": 6000,
    "data_inicio_producao": "08/07/2016",
    "fonte": "https://comunicabaciadesantos.petrobras.com.br/w/entra-em-operacao-o-decimo-grande-sistema-de-producao-no-pre-sal",
    "pais": "Brasil",
    "status": "operando"
  },
  {
    "sigla": "FPGNB",
    "nome": "FPSO GUANABARA",
    "campos": "AnC_MERO / MERO",
    "bacia": "SANTOS",
    "operador": "PETRÓLEO BRASILEIRO S.A. - PETROBRAS",
    "classificacao": "Floating Production Storage Offloading - FPSO",
    "lamina_agua_m": 1930,
    "sistema_escoamento": "Navio Aliviador",
    "ano_inicio_operacao": 2021,
    "latitude": -24.58365556,
    "longitude": -42.25626667,
    "capacidade_petroleo_bbl_d": 190000,
    "capacidade_gas_mil_m3_d": 12000,
    "data_inicio_producao": "30/04/2022",
    "fonte": "https://www.gov.br/mme/pt-br/assuntos/secretarias/petroleo-gas-natural-e-biocombustiveis/publicacoes-1/relatorio-de-atividades-relacionadas-aos-contratos-de-partilha-producao-de-petroleo-e-gas-natural/relatorios-publicados/relatorio-sem-1-2025",
    "pais": "Brasil",
    "status": "operando"
  },
  {
    "sigla": "FPMDC",
    "nome": "FPSO MARECHAL DUQUE DE CAXIAS",
    "campos": "AnC_MERO / MERO",
    "bacia": "SANTOS",
    "operador": "PETRÓLEO BRASILEIRO S.A. - PETROBRAS",
    "classificacao": "Floating Production Storage Offloading - FPSO",
    "lamina_agua_m": 2070,
    "sistema_escoamento": "Navio Aliviador",
    "ano_inicio_operacao": 2024,
    "latitude": -24.68622167,
    "longitude": -42.29323194,
    "capacidade_petroleo_bbl_d": 200000,
    "capacidade_gas_mil_m3_d": 13500,
    "data_inicio_producao": "30/10/2024",
    "fonte": "https://agencia.petrobras.com.br/w/negocio/petrobras-atinge-recordes-na-producao-do-pre-sal-em-2024-e-tem-maior-fator-de-utilizacao-das-suas-refinarias-em-10-anos",
    "pais": "Brasil",
    "status": "operando"
  },
  {
    "sigla": "FPMQT",
    "nome": "FPSO MARIA QUITÉRIA",
    "campos": "AnC_Jubarte_Nordeste / AnC_Jubarte_Sudoeste / ARGONAUTA / JUBARTE",
    "bacia": "CAMPOS",
    "operador": "PETRÓLEO BRASILEIRO S.A. - PETROBRAS",
    "classificacao": "Floating Production Storage Offloading - FPSO",
    "lamina_agua_m": 1385,
    "sistema_escoamento": "Navio Aliviador e Duto",
    "ano_inicio_operacao": 2024,
    "latitude": -21.27003889,
    "longitude": -39.99762222,
    "capacidade_petroleo_bbl_d": 100000,
    "capacidade_gas_mil_m3_d": 5000,
    "data_inicio_producao": "15/10/2024",
    "fonte": "https://agencia.petrobras.com.br/w/negocio/petrobras-atinge-recordes-na-producao-do-pre-sal-em-2024-e-tem-maior-fator-de-utilizacao-das-suas-refinarias-em-10-anos",
    "pais": "Brasil",
    "status": "operando"
  },
  {
    "sigla": "FPPL",
    "nome": "FPSO PIONEIRO DE LIBRA",
    "campos": "AnC_MERO / MERO",
    "bacia": "SANTOS",
    "operador": "PETRÓLEO BRASILEIRO S.A. - PETROBRAS",
    "classificacao": "Floating Production Storage Offloading - FPSO",
    "lamina_agua_m": 1920,
    "sistema_escoamento": "Navio Aliviador",
    "ano_inicio_operacao": 2017,
    "latitude": -24.54004972,
    "longitude": -42.13184361,
    "capacidade_petroleo_bbl_d": 50318,
    "capacidade_gas_mil_m3_d": 4000,
    "data_inicio_producao": "26/11/2017",
    "fonte": "https://comunicabaciadesantos.petrobras.com.br/w/petrobras-e-seus-parceiros-iniciam-producao-de-libra",
    "pais": "Brasil",
    "status": "operando"
  },
  {
    "sigla": "FPSO_CRC",
    "nome": "FPSO CARIOCA",
    "campos": "SÉPIA / SÉPIA LESTE / SÉPIA_ECO",
    "bacia": "SANTOS",
    "operador": "PETRÓLEO BRASILEIRO S.A. - PETROBRAS",
    "classificacao": "Floating Production Storage Offloading - FPSO",
    "lamina_agua_m": 2140,
    "sistema_escoamento": "Navio Aliviador",
    "ano_inicio_operacao": 2021,
    "latitude": -25.22704306,
    "longitude": -42.5702525,
    "capacidade_petroleo_bbl_d": 180000,
    "capacidade_gas_mil_m3_d": 6091,
    "data_inicio_producao": "23/08/2021",
    "fonte": "https://agencia.petrobras.com.br/w/plataforma-de-maior-producao-atualmente-da-petrobras-o-fpso-carioca-completa-um-ano-de-operacao",
    "pais": "Brasil",
    "status": "operando"
  },
  {
    "sigla": "FPSTB",
    "nome": "FPSO SEPETIBA",
    "campos": "AnC_MERO / MERO",
    "bacia": "SANTOS",
    "operador": "PETRÓLEO BRASILEIRO S.A. - PETROBRAS",
    "classificacao": "Floating Production Storage Offloading - FPSO",
    "lamina_agua_m": 2000,
    "sistema_escoamento": "Navio Aliviador",
    "ano_inicio_operacao": 2023,
    "latitude": -24.63081444,
    "longitude": -42.26445806,
    "capacidade_petroleo_bbl_d": 190000,
    "capacidade_gas_mil_m3_d": 12000,
    "data_inicio_producao": "31/12/2023",
    "fonte": "https://agencia.petrobras.com.br/en/w/petrobras-coloca-o-navio-plataforma-sepetiba-em-producao-no-pre-sal",
    "pais": "Brasil",
    "status": "operando"
  },
  {
    "sigla": "FPTAM",
    "nome": "FPSO ALMIRANTE TAMANDARE",
    "campos": "BÚZIOS / BÚZIOS_ECO / TAMBUATÁ",
    "bacia": "SANTOS",
    "operador": "PETRÓLEO BRASILEIRO S.A. - PETROBRAS",
    "classificacao": "Floating Production Storage Offloading - FPSO",
    "lamina_agua_m": 1985,
    "sistema_escoamento": "Navio Aliviador",
    "ano_inicio_operacao": 2025,
    "latitude": -24.74358333,
    "longitude": -42.51331944,
    "capacidade_petroleo_bbl_d": 225000,
    "capacidade_gas_mil_m3_d": 12000,
    "data_inicio_producao": "15/02/2025",
    "fonte": "https://agencia.petrobras.com.br/w/negocio/fpso-almirante-tamandare-inicia-producao-no-pre-sal",
    "pais": "Brasil",
    "status": "operando"
  },
  {
    "sigla": "P-40",
    "nome": "PETROBRAS 40",
    "campos": "MARLIM / MARLIM LESTE / MARLIM SUL",
    "bacia": "CAMPOS",
    "operador": "PETRÓLEO BRASILEIRO S.A. - PETROBRAS",
    "classificacao": "Semissubmersível - SS",
    "lamina_agua_m": 1080,
    "sistema_escoamento": "Duto",
    "ano_inicio_operacao": 2001,
    "latitude": -22.54742194,
    "longitude": -40.06744306,
    "capacidade_petroleo_bbl_d": 202846,
    "capacidade_gas_mil_m3_d": 6000,
    "data_inicio_producao": "16/12/2001",
    "fonte": "https://comunicaespiritosanto.petrobras.com.br/documents/d/comunica-espirito-santo/c763-dt28_rev00_final-1-1?download=true",
    "pais": "Brasil",
    "status": "operando"
  },
  {
    "sigla": "P-43",
    "nome": "PETROBRAS 43",
    "campos": "BARRACUDA / CARATINGA",
    "bacia": "CAMPOS",
    "operador": "PETRÓLEO BRASILEIRO S.A. - PETROBRAS",
    "classificacao": "Floating Production Storage Offloading - FPSO",
    "lamina_agua_m": 800,
    "sistema_escoamento": "Navio Aliviador",
    "ano_inicio_operacao": 2004,
    "latitude": -22.55011,
    "longitude": -40.25944889,
    "capacidade_petroleo_bbl_d": 174000,
    "capacidade_gas_mil_m3_d": 6000,
    "data_inicio_producao": "22/12/2004",
    "fonte": "https://www.ogj.com/drilling-production/article/17244620/p-43-fpso-producing-off-brazil-p-48-due",
    "pais": "Brasil",
    "status": "operando"
  },
  {
    "sigla": "P-48",
    "nome": "PETROBRAS 48",
    "campos": "BARRACUDA / CARATINGA",
    "bacia": "CAMPOS",
    "operador": "PETRÓLEO BRASILEIRO S.A. - PETROBRAS",
    "classificacao": "Floating Production Storage Offloading - FPSO",
    "lamina_agua_m": 1032,
    "sistema_escoamento": "Navio Aliviador",
    "ano_inicio_operacao": 2005,
    "latitude": -22.66388389,
    "longitude": -40.24018889,
    "capacidade_petroleo_bbl_d": 150000,
    "capacidade_gas_mil_m3_d": 6000,
    "data_inicio_producao": "28/02/2005",
    "fonte": "https://www.tribunapr.com.br/noticias/plataforma-p-48-comecou-a-produzir-hoje/",
    "pais": "Brasil",
    "status": "operando"
  },
  {
    "sigla": "P-51",
    "nome": "PETROBRAS 51",
    "campos": "MARLIM SUL",
    "bacia": "CAMPOS",
    "operador": "PETRÓLEO BRASILEIRO S.A. - PETROBRAS",
    "classificacao": "Semissubmersível - SS",
    "lamina_agua_m": 1260,
    "sistema_escoamento": "Duto",
    "ano_inicio_operacao": 2009,
    "latitude": -22.63440278,
    "longitude": -40.09363722,
    "capacidade_petroleo_bbl_d": 180000,
    "capacidade_gas_mil_m3_d": 6000,
    "data_inicio_producao": "24/01/2009",
    "fonte": "https://pt.wikipedia.org/wiki/Plataforma_P-51",
    "pais": "Brasil",
    "status": "operando"
  },
  {
    "sigla": "P-53",
    "nome": "PETROBRAS 53",
    "campos": "MARLIM LESTE",
    "bacia": "CAMPOS",
    "operador": "PETRÓLEO BRASILEIRO S.A. - PETROBRAS",
    "classificacao": "Floating Production Storage Offloading - FPSO",
    "lamina_agua_m": 1068,
    "sistema_escoamento": "Duto",
    "ano_inicio_operacao": 2008,
    "latitude": -22.42401667,
    "longitude": -39.95766667,
    "capacidade_petroleo_bbl_d": 180000,
    "capacidade_gas_mil_m3_d": 6000,
    "data_inicio_producao": "30/11/2008",
    "fonte": "https://ptdocz.com/doc/230645/energ%C3%A9tica---casa-civil",
    "pais": "Brasil",
    "status": "operando"
  },
  {
    "sigla": "P-54",
    "nome": "PETROBRAS 54",
    "campos": "RONCADOR",
    "bacia": "CAMPOS",
    "operador": "PETRÓLEO BRASILEIRO S.A. - PETROBRAS",
    "classificacao": "Floating Production Storage Offloading - FPSO",
    "lamina_agua_m": 1400,
    "sistema_escoamento": "Navio Aliviador",
    "ano_inicio_operacao": 2007,
    "latitude": -21.96911389,
    "longitude": -39.82530278,
    "capacidade_petroleo_bbl_d": 190000,
    "capacidade_gas_mil_m3_d": 4000,
    "data_inicio_producao": "12/12/2007",
    "fonte": "https://www.jb.com.br/economia/noticias/2007/12/12/p-54-comeca-a-operar-no-campo-de-roncador.html",
    "pais": "Brasil",
    "status": "operando"
  },
  {
    "sigla": "P-55",
    "nome": "PETROBRAS 55",
    "campos": "RONCADOR",
    "bacia": "CAMPOS",
    "operador": "PETRÓLEO BRASILEIRO S.A. - PETROBRAS",
    "classificacao": "Semissubmersível - SS",
    "lamina_agua_m": 1795,
    "sistema_escoamento": "Duto",
    "ano_inicio_operacao": 2014,
    "latitude": -21.99321972,
    "longitude": -39.73953889,
    "capacidade_petroleo_bbl_d": 180000,
    "capacidade_gas_mil_m3_d": 4000,
    "data_inicio_producao": "31/12/2013",
    "fonte": "https://www.sec.gov/Archives/edgar/data/1119639/000129281414000002/pbra20140102_6k.htm",
    "pais": "Brasil",
    "status": "operando"
  },
  {
    "sigla": "P-56",
    "nome": "PETROBRAS 56",
    "campos": "MARLIM SUL",
    "bacia": "CAMPOS",
    "operador": "PETRÓLEO BRASILEIRO S.A. - PETROBRAS",
    "classificacao": "Semissubmersível - SS",
    "lamina_agua_m": 1645,
    "sistema_escoamento": "Duto",
    "ano_inicio_operacao": 2011,
    "latitude": -22.62404167,
    "longitude": -39.98948333,
    "capacidade_petroleo_bbl_d": 141000,
    "capacidade_gas_mil_m3_d": 6000,
    "data_inicio_producao": "15/08/2011",
    "fonte": "https://mz-filemanager.s3.amazonaws.com/25fdf098-34f5-4608-b7fa-17d60b2de47d/comunicados-ao-mercadocentral-de-downloads/a27b19de0c9cf664ab060dc221354cb5b57d06a6f040ba9d1aebf06e2b5b6002/platform_p56_begins_production_in_marlim_sul_field.pdf",
    "pais": "Brasil",
    "status": "operando"
  },
  {
    "sigla": "P-57",
    "nome": "PETROBRAS 57",
    "campos": "JUBARTE",
    "bacia": "CAMPOS",
    "operador": "PETRÓLEO BRASILEIRO S.A. - PETROBRAS",
    "classificacao": "Floating Production Storage Offloading - FPSO",
    "lamina_agua_m": 1258,
    "sistema_escoamento": "Navio Aliviador",
    "ano_inicio_operacao": 2010,
    "latitude": -21.24001111,
    "longitude": -40.04807778,
    "capacidade_petroleo_bbl_d": 180000,
    "capacidade_gas_mil_m3_d": 2000,
    "data_inicio_producao": "17/12/2010",
    "fonte": "https://www.offshore-energy.biz/sbm-offshore-fpso-p-57-starts-first-oil-production-off-brazil/",
    "pais": "Brasil",
    "status": "operando"
  },
  {
    "sigla": "P-58",
    "nome": "PETROBRAS 58",
    "campos": "AnC_Jubarte_Nordeste / AnC_Jubarte_Sudoeste / ARGONAUTA / BALEIA ANÃ / JUBARTE",
    "bacia": "CAMPOS",
    "operador": "PETRÓLEO BRASILEIRO S.A. - PETROBRAS",
    "classificacao": "Floating Production Storage Offloading - FPSO",
    "lamina_agua_m": 1399,
    "sistema_escoamento": "Navio Aliviador",
    "ano_inicio_operacao": 2014,
    "latitude": -21.21508417,
    "longitude": -39.99736472,
    "capacidade_petroleo_bbl_d": 180018,
    "capacidade_gas_mil_m3_d": 6000,
    "data_inicio_producao": "17/03/2014",
    "fonte": "https://atarde.com.br/economia/correcao-petrobras-poe-p-58-em-operacao-587787",
    "pais": "Brasil",
    "status": "operando"
  },
  {
    "sigla": "P-62",
    "nome": "PETROBRAS 62",
    "campos": "RONCADOR",
    "bacia": "CAMPOS",
    "operador": "PETRÓLEO BRASILEIRO S.A. - PETROBRAS",
    "classificacao": "Floating Production Storage Offloading - FPSO",
    "lamina_agua_m": 1580,
    "sistema_escoamento": "Navio Aliviador",
    "ano_inicio_operacao": 2014,
    "latitude": -21.94083333,
    "longitude": -39.78611111,
    "capacidade_petroleo_bbl_d": 180000,
    "capacidade_gas_mil_m3_d": 6000,
    "data_inicio_producao": "12/05/2014",
    "fonte": "https://mz-filemanager.s3.amazonaws.com/25fdf098-34f5-4608-b7fa-17d60b2de47d/comunicados-ao-mercadocentral-de-downloads/6063a0025f81ad469f89a99fa78b64d2e6f81c0685202dcf4e472824d8322ba4/startup_of_platform_p62_in_roncador_field.pdf",
    "pais": "Brasil",
    "status": "operando"
  },
  {
    "sigla": "P-66",
    "nome": "PETROBRAS 66",
    "campos": "AnC_TUPI / SUL DE TUPI / TUPI",
    "bacia": "SANTOS",
    "operador": "PETRÓLEO BRASILEIRO S.A. - PETROBRAS",
    "classificacao": "Floating Production Storage Offloading - FPSO",
    "lamina_agua_m": 2150,
    "sistema_escoamento": "Navio Aliviador",
    "ano_inicio_operacao": 2017,
    "latitude": -25.60281861,
    "longitude": -42.8206575,
    "capacidade_petroleo_bbl_d": 150955,
    "capacidade_gas_mil_m3_d": 6000,
    "data_inicio_producao": "17/05/2017",
    "fonte": "https://comunicabaciadesantos.petrobras.com.br/w/petrobras-inicia-producao-da-plataforma-p-66",
    "pais": "Brasil",
    "status": "operando"
  },
  {
    "sigla": "P-67",
    "nome": "PETROBRAS 67",
    "campos": "AnC_TUPI / SUL DE TUPI / TUPI",
    "bacia": "SANTOS",
    "operador": "PETRÓLEO BRASILEIRO S.A. - PETROBRAS",
    "classificacao": "Floating Production Storage Offloading - FPSO",
    "lamina_agua_m": 2130,
    "sistema_escoamento": "Navio Aliviador",
    "ano_inicio_operacao": 2018,
    "latitude": -25.32987139,
    "longitude": -42.6926575,
    "capacidade_petroleo_bbl_d": 150950,
    "capacidade_gas_mil_m3_d": 6000,
    "data_inicio_producao": "01/02/2019",
    "fonte": "https://comunicabaciadesantos.petrobras.com.br/w/plataforma-p-67-inicia-producao-no-campo-de-lula-no-pre-sal-da-bacia-de-santos",
    "pais": "Brasil",
    "status": "operando"
  },
  {
    "sigla": "P-68",
    "nome": "PETROBRAS 68",
    "campos": "BERBIGÃO / SUL DE BERBIGÃO",
    "bacia": "SANTOS",
    "operador": "PETRÓLEO BRASILEIRO S.A. - PETROBRAS",
    "classificacao": "Floating Production Storage Offloading - FPSO",
    "lamina_agua_m": 2280,
    "sistema_escoamento": "Navio Aliviador",
    "ano_inicio_operacao": 2018,
    "latitude": -25.02295278,
    "longitude": -42.66778889,
    "capacidade_petroleo_bbl_d": 163000,
    "capacidade_gas_mil_m3_d": 6000,
    "data_inicio_producao": "27/11/2019",
    "fonte": "https://comunicabaciadesantos.petrobras.com.br/w/iniciamos-operacao-da-p-68-e-producao-do-campo-de-berbigao",
    "pais": "Brasil",
    "status": "operando"
  },
  {
    "sigla": "P-69",
    "nome": "PETROBRAS 69",
    "campos": "AnC_TUPI / SUL DE TUPI / TUPI",
    "bacia": "SANTOS",
    "operador": "PETRÓLEO BRASILEIRO S.A. - PETROBRAS",
    "classificacao": "Floating Production Storage Offloading - FPSO",
    "lamina_agua_m": 2170,
    "sistema_escoamento": "Navio Aliviador",
    "ano_inicio_operacao": 2018,
    "latitude": -25.65792889,
    "longitude": -42.85944306,
    "capacidade_petroleo_bbl_d": 173000,
    "capacidade_gas_mil_m3_d": 6000,
    "data_inicio_producao": "23/10/2018",
    "fonte": "https://comunicabaciadesantos.petrobras.com.br/w/navio-plataforma-p-69-entra-em-producao-no-pre-sal-da-bacia-de-santos",
    "pais": "Brasil",
    "status": "operando"
  },
  {
    "sigla": "P-70",
    "nome": "PETROBRAS 70",
    "campos": "AnC_NORTE_ATAPU / ATAPU / ATAPU_ECO / OESTE DE ATAPU",
    "bacia": "SANTOS",
    "operador": "PETRÓLEO BRASILEIRO S.A. - PETROBRAS",
    "classificacao": "Floating Production Storage Offloading - FPSO",
    "lamina_agua_m": 2288,
    "sistema_escoamento": "Navio Aliviador",
    "ano_inicio_operacao": 2020,
    "latitude": -24.95207056,
    "longitude": -42.46838,
    "capacidade_petroleo_bbl_d": 161000,
    "capacidade_gas_mil_m3_d": 6000,
    "data_inicio_producao": "25/06/2020",
    "fonte": "https://www.gov.br/mme/pt-br/assuntos/noticias/inicio-da-producao-no-pre-sal-de-atapu",
    "pais": "Brasil",
    "status": "operando"
  },
  {
    "sigla": "P-71",
    "nome": "PETROBRAS 71",
    "campos": "ITAPU / ITAPU_ECO",
    "bacia": "SANTOS",
    "operador": "PETRÓLEO BRASILEIRO S.A. - PETROBRAS",
    "classificacao": "Floating Production Storage Offloading - FPSO",
    "lamina_agua_m": 2010,
    "sistema_escoamento": "Navio Aliviador",
    "ano_inicio_operacao": 2023,
    "latitude": -24.777175,
    "longitude": -42.72058333,
    "capacidade_petroleo_bbl_d": 150955,
    "capacidade_gas_mil_m3_d": 6000,
    "data_inicio_producao": "21/12/2022",
    "fonte": "https://agencia.petrobras.com.br/pt/w/negocio/petrobras-coloca-em-producao-plataforma-p-71-no-pre-sal-da-bacia-de-santos",
    "pais": "Brasil",
    "status": "operando"
  },
  {
    "sigla": "P-74",
    "nome": "PETROBRAS 74",
    "campos": "BÚZIOS / BÚZIOS_ECO / TAMBUATÁ",
    "bacia": "SANTOS",
    "operador": "PETRÓLEO BRASILEIRO S.A. - PETROBRAS",
    "classificacao": "Floating Production Storage Offloading - FPSO",
    "lamina_agua_m": 1950,
    "sistema_escoamento": "Navio Aliviador",
    "ano_inicio_operacao": 2018,
    "latitude": -24.64806556,
    "longitude": -42.51781444,
    "capacidade_petroleo_bbl_d": 154000,
    "capacidade_gas_mil_m3_d": 7000,
    "data_inicio_producao": "20/04/2018",
    "fonte": "https://antigo.mme.gov.br/documents/36212/439850/Boletim%2BDEPG%2Bedi%C3%A7%C3%A3o%2B72%2B-%2Babr2018.pdf/0367e596-c7f0-1f59-f295-234c4b1633e4?version=1.0",
    "pais": "Brasil",
    "status": "operando"
  },
  {
    "sigla": "P-75",
    "nome": "PETROBRAS 75",
    "campos": "BÚZIOS / BÚZIOS_ECO / TAMBUATÁ",
    "bacia": "SANTOS",
    "operador": "PETRÓLEO BRASILEIRO S.A. - PETROBRAS",
    "classificacao": "Floating Production Storage Offloading - FPSO",
    "lamina_agua_m": 2015,
    "sistema_escoamento": "Navio Aliviador",
    "ano_inicio_operacao": 2018,
    "latitude": -24.78901472,
    "longitude": -42.50973611,
    "capacidade_petroleo_bbl_d": 169000,
    "capacidade_gas_mil_m3_d": 7000,
    "data_inicio_producao": "11/11/2018",
    "fonte": "https://comunicabaciadesantos.petrobras.com.br/documents/1286238/1532749/10_Informe%20Bacia%20de%20Santos_10_final.pdf/665590a9-34e7-4323-665f-fce5c6bc416c?download=true",
    "pais": "Brasil",
    "status": "operando"
  },
  {
    "sigla": "P-76",
    "nome": "PETROBRAS 76",
    "campos": "BÚZIOS / BÚZIOS_ECO / TAMBUATÁ",
    "bacia": "SANTOS",
    "operador": "PETRÓLEO BRASILEIRO S.A. - PETROBRAS",
    "classificacao": "Floating Production Storage Offloading - FPSO",
    "lamina_agua_m": 2025,
    "sistema_escoamento": "Navio Aliviador",
    "ano_inicio_operacao": 2018,
    "latitude": -24.68898056,
    "longitude": -42.50583056,
    "capacidade_petroleo_bbl_d": 169000,
    "capacidade_gas_mil_m3_d": 7000,
    "data_inicio_producao": "20/02/2019",
    "fonte": "https://comunicabaciadesantos.petrobras.com.br/w/petrobras-inicia-producao-na-p-76-e-na-p-77-no-campo-de-buzios-no-pre-sal-da-bacia-de-santos",
    "pais": "Brasil",
    "status": "operando"
  },
  {
    "sigla": "P-77",
    "nome": "PETROBRAS 77",
    "campos": "BÚZIOS / BÚZIOS_ECO / TAMBUATÁ",
    "bacia": "SANTOS",
    "operador": "PETRÓLEO BRASILEIRO S.A. - PETROBRAS",
    "classificacao": "Floating Production Storage Offloading - FPSO",
    "lamina_agua_m": 1980,
    "sistema_escoamento": "Navio Aliviador",
    "ano_inicio_operacao": 2019,
    "latitude": -24.63649611,
    "longitude": -42.41198972,
    "capacidade_petroleo_bbl_d": 169000,
    "capacidade_gas_mil_m3_d": 7000,
    "data_inicio_producao": "19/03/2019",
    "fonte": "https://comunicabaciadesantos.petrobras.com.br/w/petrobras-inicia-producao-na-p-76-e-na-p-77-no-campo-de-buzios-no-pre-sal-da-bacia-de-santos",
    "pais": "Brasil",
    "status": "operando"
  },
  {
    "sigla": "P-78",
    "nome": "PETROBRAS 78",
    "campos": "BÚZIOS / BÚZIOS_ECO / TAMBUATÁ",
    "bacia": "SANTOS",
    "operador": "PETRÓLEO BRASILEIRO S.A. - PETROBRAS",
    "classificacao": "Floating Production Storage Offloading - FPSO",
    "lamina_agua_m": 2030,
    "sistema_escoamento": "Navio Aliviador e Duto",
    "ano_inicio_operacao": 2025,
    "latitude": -24.68023944,
    "longitude": -42.38285028,
    "capacidade_petroleo_bbl_d": 180000,
    "capacidade_gas_mil_m3_d": 7200,
    "data_inicio_producao": "31/12/2025",
    "fonte": "https://agencia.petrobras.com.br/w/petrobras-inicia-produ%C3%A7%C3%A3o-de-b%C3%BAzios-6",
    "pais": "Brasil",
    "status": "operando"
  },
  {
    "sigla": "PARB1",
    "nome": "PLATAFORMA DE ARABAIANA 1",
    "campos": "ARABAIANA",
    "bacia": "POTIGUAR",
    "operador": "PETRÓLEO BRASILEIRO S.A. - PETROBRAS",
    "classificacao": "Plataforma Fixa - Caisson",
    "lamina_agua_m": 30,
    "sistema_escoamento": "Duto",
    "ano_inicio_operacao": 2001,
    "latitude": -4.69477028,
    "longitude": -36.72455639,
    "capacidade_petroleo_bbl_d": null,
    "capacidade_gas_mil_m3_d": null,
    "data_inicio_producao": "06/08/2002",
    "fonte": "https://www.gov.br/anp/pt-br/assuntos/exploracao-e-producao-de-oleo-e-gas/desenvolvimento-e-producao/pd/arabaiana.pdf",
    "pais": "Brasil",
    "status": "operando"
  },
  {
    "sigla": "PGP-1",
    "nome": "PLATAFORMA DE GAROUPA",
    "campos": "GAROUPA",
    "bacia": "CAMPOS",
    "operador": "PETRÓLEO BRASILEIRO S.A. - PETROBRAS",
    "classificacao": "Plataforma Fixa - Jaqueta",
    "lamina_agua_m": 120,
    "sistema_escoamento": "Duto",
    "ano_inicio_operacao": 1984,
    "latitude": -22.37477944,
    "longitude": -40.417455,
    "capacidade_petroleo_bbl_d": 57080,
    "capacidade_gas_mil_m3_d": 3000,
    "data_inicio_producao": "01/07/1984",
    "fonte": "https://comunicaespiritosanto.petrobras.com.br/documents/d/comunica-espirito-santo/c763-dt28_rev00_final-1-1?download=true",
    "pais": "Brasil",
    "status": "operando"
  },
  {
    "sigla": "PMNT",
    "nome": "PLATAFORMA DE MANATI",
    "campos": "MANATI",
    "bacia": "CAMAMU",
    "operador": "PETRÓLEO BRASILEIRO S.A. - PETROBRAS",
    "classificacao": "Plataforma Fixa - Jaqueta",
    "lamina_agua_m": 37,
    "sistema_escoamento": "Duto",
    "ano_inicio_operacao": 2007,
    "latitude": -13.48997389,
    "longitude": -38.81231333,
    "capacidade_petroleo_bbl_d": null,
    "capacidade_gas_mil_m3_d": 6,
    "data_inicio_producao": "09/02/2007",
    "fonte": "https://www.ba.gov.br/comunicacao/2007/09/noticias/empresa-japonesa-quer-aumentar-investimentos-na-area-de-gas-natural",
    "pais": "Brasil",
    "status": "operando"
  },
  {
    "sigla": "PMXL-1",
    "nome": "PLATAFORMA DE MEXILHÃO",
    "campos": "MEXILHÃO",
    "bacia": "SANTOS",
    "operador": "PETRÓLEO BRASILEIRO S.A. - PETROBRAS",
    "classificacao": "Plataforma Fixa - Jaqueta",
    "lamina_agua_m": 172,
    "sistema_escoamento": "Duto",
    "ano_inicio_operacao": 2011,
    "latitude": -24.35316389,
    "longitude": -44.38281361,
    "capacidade_petroleo_bbl_d": 19554,
    "capacidade_gas_mil_m3_d": 150000,
    "data_inicio_producao": "19/04/2011",
    "fonte": "https://www.marinha.mil.br/dpc/sites/www.marinha.mil.br.dpc/files/PLATAFORMAS-PETROLEO08JUNHO2025.pdf",
    "pais": "Brasil",
    "status": "operando"
  },
  {
    "sigla": "PPE02",
    "nome": "PLATAFORMA DE PESCADA 2",
    "campos": "PESCADA",
    "bacia": "POTIGUAR",
    "operador": "PETRÓLEO BRASILEIRO S.A. - PETROBRAS",
    "classificacao": "Plataforma Fixa - Caisson",
    "lamina_agua_m": 17,
    "sistema_escoamento": "Duto",
    "ano_inicio_operacao": 1999,
    "latitude": -4.71841806,
    "longitude": -36.83579444,
    "capacidade_petroleo_bbl_d": null,
    "capacidade_gas_mil_m3_d": null,
    "data_inicio_producao": "01/05/1999",
    "fonte": "https://www.gov.br/anp/pt-br/assuntos/exploracao-e-producao-de-oleo-e-gas/desenvolvimento-e-producao/pd/pescada.pdf",
    "pais": "Brasil",
    "status": "operando"
  },
  {
    "sigla": "PPE1B",
    "nome": "PLATAFORMA DE PESCADA 1B",
    "campos": "PESCADA",
    "bacia": "POTIGUAR",
    "operador": "PETRÓLEO BRASILEIRO S.A. - PETROBRAS",
    "classificacao": "Plataforma Fixa - Caisson",
    "lamina_agua_m": 17,
    "sistema_escoamento": "Duto",
    "ano_inicio_operacao": 1998,
    "latitude": -4.70450833,
    "longitude": -36.825635,
    "capacidade_petroleo_bbl_d": null,
    "capacidade_gas_mil_m3_d": null,
    "data_inicio_producao": "01/05/1999",
    "fonte": "https://www.gov.br/anp/pt-br/assuntos/exploracao-e-producao-de-oleo-e-gas/desenvolvimento-e-producao/pd/pescada.pdf",
    "pais": "Brasil",
    "status": "operando"
  },
  {
    "sigla": "BRAVO",
    "nome": "FPSO BRAVO",
    "campos": "TUBARÃO MARTELO",
    "bacia": "CAMPOS",
    "operador": "PRIO BRAVO LTDA.",
    "classificacao": "Floating Production Storage Offloading - FPSO",
    "lamina_agua_m": 105,
    "sistema_escoamento": "Navio Aliviador",
    "ano_inicio_operacao": 2013,
    "latitude": -23.13582222,
    "longitude": -41.07353056,
    "capacidade_petroleo_bbl_d": 100000,
    "capacidade_gas_mil_m3_d": 1500,
    "data_inicio_producao": "06/12/2013",
    "fonte": "https://oglobo.globo.com/economia/ogx-inicia-producao-de-petroleo-em-tubarao-martelo-2-10989283",
    "pais": "Brasil",
    "status": "operando"
  },
  {
    "sigla": "POLVO A",
    "nome": "POLVO A",
    "campos": "POLVO",
    "bacia": "CAMPOS",
    "operador": "PRIO BRAVO LTDA.",
    "classificacao": "Plataforma Fixa - Jaqueta",
    "lamina_agua_m": 105,
    "sistema_escoamento": "Duto",
    "ano_inicio_operacao": 2007,
    "latitude": -23.08381389,
    "longitude": -40.99542917,
    "capacidade_petroleo_bbl_d": null,
    "capacidade_gas_mil_m3_d": null,
    "data_inicio_producao": "24/07/2007",
    "fonte": "https://www.offshore-mag.com/business-briefs/company-news/article/16761862/devon-breaks-new-ground-at-polvo",
    "pais": "Brasil",
    "status": "operando"
  },
  {
    "sigla": "FORTE",
    "nome": "FPSO FORTE",
    "campos": "ALBACORA / ALBACORA LESTE",
    "bacia": "CAMPOS",
    "operador": "PRIO FORTE S.A.",
    "classificacao": "Floating Production Storage Offloading - FPSO",
    "lamina_agua_m": 1230,
    "sistema_escoamento": "Navio Aliviador",
    "ano_inicio_operacao": 2006,
    "latitude": -22.08638778,
    "longitude": -39.82799861,
    "capacidade_petroleo_bbl_d": 180000,
    "capacidade_gas_mil_m3_d": 6000,
    "data_inicio_producao": "21/04/2006",
    "fonte": "https://w1files.solucaoatrio.net.br/atrio/ufrj-peno_upl/THESIS/6000274/2013_mestrando_julio_cesar_fernandez_polo_20200405194940605.pdf",
    "pais": "Brasil",
    "status": "operando"
  },
  {
    "sigla": "FRADE",
    "nome": "FPSO FRADE",
    "campos": "FRADE",
    "bacia": "CAMPOS",
    "operador": "PRIO FORTE S.A.",
    "classificacao": "Floating Production Storage Offloading - FPSO",
    "lamina_agua_m": 0,
    "sistema_escoamento": "Navio Aliviador",
    "ano_inicio_operacao": 2009,
    "latitude": -21.88333333,
    "longitude": -39.85138889,
    "capacidade_petroleo_bbl_d": 100000,
    "capacidade_gas_mil_m3_d": 3,
    "data_inicio_producao": "20/06/2009",
    "fonte": "https://www.sbmoffshore.com/wp-content/uploads/2024/03/pressrelease-20090702-original-507.pdf",
    "pais": "Brasil",
    "status": "operando"
  },
  {
    "sigla": "PEREGRINO 1",
    "nome": "FPSO PEREGRINO",
    "campos": "PEREGRINO",
    "bacia": "CAMPOS",
    "operador": "PRIO TIGRIS S.A",
    "classificacao": "Floating Production Storage Offloading - FPSO",
    "lamina_agua_m": 98,
    "sistema_escoamento": "Navio Aliviador",
    "ano_inicio_operacao": 2011,
    "latitude": -23.31725556,
    "longitude": -41.25740278,
    "capacidade_petroleo_bbl_d": 18239,
    "capacidade_gas_mil_m3_d": 364,
    "data_inicio_producao": "09/04/2011",
    "fonte": "https://www.equinor.com/news/archive/2011/05/04/1Q2011Results",
    "pais": "Brasil",
    "status": "operando"
  },
  {
    "sigla": "PEREGRINO A",
    "nome": "PEREGRINO A",
    "campos": "PEREGRINO",
    "bacia": "CAMPOS",
    "operador": "PRIO TIGRIS S.A",
    "classificacao": "Plataforma Fixa - Jaqueta",
    "lamina_agua_m": 105,
    "sistema_escoamento": "Duto",
    "ano_inicio_operacao": 2011,
    "latitude": -23.33383889,
    "longitude": -41.29797222,
    "capacidade_petroleo_bbl_d": null,
    "capacidade_gas_mil_m3_d": null,
    "data_inicio_producao": "09/04/2011",
    "fonte": "https://www.equinor.com/news/archive/2011/05/04/1Q2011Results",
    "pais": "Brasil",
    "status": "operando"
  },
  {
    "sigla": "PEREGRINO B",
    "nome": "PEREGRINO B",
    "campos": "PEREGRINO",
    "bacia": "CAMPOS",
    "operador": "PRIO TIGRIS S.A",
    "classificacao": "Plataforma Fixa - Jaqueta",
    "lamina_agua_m": 121,
    "sistema_escoamento": "Duto",
    "ano_inicio_operacao": 2011,
    "latitude": -23.29541667,
    "longitude": -41.20739167,
    "capacidade_petroleo_bbl_d": null,
    "capacidade_gas_mil_m3_d": null,
    "data_inicio_producao": "09/04/2011",
    "fonte": "https://www.equinor.com/news/archive/2011/05/04/1Q2011Results",
    "pais": "Brasil",
    "status": "operando"
  },
  {
    "sigla": "WHPC",
    "nome": "PEREGRINO C",
    "campos": "PEREGRINO / PITANGOLA",
    "bacia": "CAMPOS",
    "operador": "PRIO TIGRIS S.A",
    "classificacao": "Plataforma Fixa - Jaqueta",
    "lamina_agua_m": 121,
    "sistema_escoamento": "Duto",
    "ano_inicio_operacao": 2021,
    "latitude": -23.34819333,
    "longitude": -41.40877444,
    "capacidade_petroleo_bbl_d": null,
    "capacidade_gas_mil_m3_d": null,
    "data_inicio_producao": "10/10/2022",
    "fonte": "https://www.equinor.com/no/nyheter/20221013-peregrino-fase-2-produserer",
    "pais": "Brasil",
    "status": "operando"
  },
  {
    "sigla": "FPSO ESP SANTO",
    "nome": "FPSO ESPIRITO SANTO",
    "campos": "ABALONE / AnC_ARGONAUTA_ME1 / ARGONAUTA / OSTRA",
    "bacia": "CAMPOS",
    "operador": "SHELL BRASIL PETRÓLEO LTDA.",
    "classificacao": "Floating Production Storage Offloading - FPSO",
    "lamina_agua_m": 1780,
    "sistema_escoamento": "Navio Aliviador",
    "ano_inicio_operacao": 2009,
    "latitude": -21.20857056,
    "longitude": -39.74271472,
    "capacidade_petroleo_bbl_d": 100000,
    "capacidade_gas_mil_m3_d": 177,
    "data_inicio_producao": "01/07/2009",
    "fonte": "https://www.offshore-mag.com/subsea/article/16757982/bc-10-starts-first-fully-subsea-producing-system",
    "pais": "Brasil",
    "status": "operando"
  },
  {
    "sigla": "FPCCG",
    "nome": "FPSO CIDADE DE CARAGUATATUBA - CCG (MV-27)",
    "campos": "LAPA",
    "bacia": "SANTOS",
    "operador": "TOTALENERGIES EP BRASIL LTDA.",
    "classificacao": "Floating Production Storage Offloading - FPSO",
    "lamina_agua_m": 2140,
    "sistema_escoamento": "Navio Aliviador",
    "ano_inicio_operacao": 2016,
    "latitude": -25.51872556,
    "longitude": -43.46654667,
    "capacidade_petroleo_bbl_d": 120764,
    "capacidade_gas_mil_m3_d": 4739,
    "data_inicio_producao": "19/12/2016",
    "fonte": "https://www.modec.com/news/2016/20161226.html",
    "pais": "Brasil",
    "status": "operando"
  },
  {
    "sigla": "P-08",
    "nome": "PLATAFORMA 08",
    "campos": "MARIMBÁ",
    "bacia": "CAMPOS",
    "operador": "TRIDENT ENERGY DO BRASIL LTDA.",
    "classificacao": "Semissubmersível - SS",
    "lamina_agua_m": 423,
    "sistema_escoamento": "Duto",
    "ano_inicio_operacao": 1993,
    "latitude": -22.67308694,
    "longitude": -40.54650556,
    "capacidade_petroleo_bbl_d": null,
    "capacidade_gas_mil_m3_d": null,
    "data_inicio_producao": "30/04/1985",
    "fonte": "https://www.gov.br/anp/pt-br/assuntos/exploracao-e-producao-de-oleo-e-gas/desenvolvimento-e-producao/pd/marimba.pdf/@@download/file",
    "pais": "Brasil",
    "status": "operando"
  },
  {
    "sigla": "P-65",
    "nome": "PLATAFORMA 65",
    "campos": "BONITO / ENCHOVA",
    "bacia": "CAMPOS",
    "operador": "TRIDENT ENERGY DO BRASIL LTDA.",
    "classificacao": "Semissubmersível - SS",
    "lamina_agua_m": 120,
    "sistema_escoamento": "Duto",
    "ano_inicio_operacao": 1966,
    "latitude": -22.70183667,
    "longitude": -40.67710639,
    "capacidade_petroleo_bbl_d": 33320,
    "capacidade_gas_mil_m3_d": 49,
    "data_inicio_producao": "01/04/2003",
    "fonte": "https://www.gov.br/anp/pt-br/assuntos/exploracao-e-producao-de-oleo-e-gas/seguranca-operacional/arq/ppdi/PDI_C_P_65.pdf",
    "pais": "Brasil",
    "status": "operando"
  },
  {
    "sigla": "PCE-1",
    "nome": "PLATAFORMA DE ENCHOVA",
    "campos": "BONITO / ENCHOVA / ENCHOVA OESTE",
    "bacia": "CAMPOS",
    "operador": "TRIDENT ENERGY DO BRASIL LTDA.",
    "classificacao": "Plataforma Fixa - Jaqueta",
    "lamina_agua_m": 116,
    "sistema_escoamento": "Duto",
    "ano_inicio_operacao": 1983,
    "latitude": -22.70836167,
    "longitude": -40.693215,
    "capacidade_petroleo_bbl_d": 98121,
    "capacidade_gas_mil_m3_d": 3895,
    "data_inicio_producao": "01/08/1977",
    "fonte": "https://www.gov.br/anp/pt-br/assuntos/exploracao-e-producao-de-oleo-e-gas/desenvolvimento-e-producao/pd/enchova.pdf/@@download/file",
    "pais": "Brasil",
    "status": "operando"
  },
  {
    "sigla": "PPM-1",
    "nome": "PLATAFORMA DE PAMPO 1",
    "campos": "LINGUADO / PAMPO",
    "bacia": "CAMPOS",
    "operador": "TRIDENT ENERGY DO BRASIL LTDA.",
    "classificacao": "Plataforma Fixa - Jaqueta",
    "lamina_agua_m": 115,
    "sistema_escoamento": "Duto",
    "ano_inicio_operacao": 1984,
    "latitude": -22.7980075,
    "longitude": -40.76254444,
    "capacidade_petroleo_bbl_d": 14300,
    "capacidade_gas_mil_m3_d": 144,
    "data_inicio_producao": "06/08/1998",
    "fonte": "https://www.gov.br/anp/pt-br/assuntos/exploracao-e-producao-de-oleo-e-gas/desenvolvimento-e-producao/pd/pampo.pdf/@@download/file",
    "pais": "Brasil",
    "status": "operando"
  }
]